setup.py
daniel_udacity/Binomialdistribution.py
daniel_udacity/Gaussiandistribution.py
daniel_udacity/Generaldistribution.py
daniel_udacity/__init__.py
daniel_udacity.egg-info/PKG-INFO
daniel_udacity.egg-info/SOURCES.txt
daniel_udacity.egg-info/dependency_links.txt
daniel_udacity.egg-info/not-zip-safe
daniel_udacity.egg-info/top_level.txt