Metadata-Version: 1.0
Name: daniel-udacity
Version: 0.1
Summary: Gaussian distributions
Home-page: UNKNOWN
Author: Daniel Grzebyk
Author-email: UNKNOWN
License: UNKNOWN
Platform: UNKNOWN
